skyfield/__init__.py
skyfield/__main__.py
skyfield/_compatibility.py
skyfield/almanac.py
skyfield/almanac_east_asia.py
skyfield/api.py
skyfield/constants.py
skyfield/constellationlib.py
skyfield/curvelib.py
skyfield/descriptorlib.py
skyfield/earthlib.py
skyfield/eclipselib.py
skyfield/elementslib.py
skyfield/errors.py
skyfield/framelib.py
skyfield/functions.py
skyfield/geometry.py
skyfield/io_timescale.py
skyfield/iokit.py
skyfield/jpllib.py
skyfield/keplerlib.py
skyfield/magnitudelib.py
skyfield/naifcodes.py
skyfield/named_stars.py
skyfield/nutationlib.py
skyfield/planetarylib.py
skyfield/positionlib.py
skyfield/precessionlib.py
skyfield/projections.py
skyfield/relativity.py
skyfield/searchlib.py
skyfield/sgp4lib.py
skyfield/starlib.py
skyfield/timelib.py
skyfield/toposlib.py
skyfield/trigonometry.py
skyfield/units.py
skyfield/vectorlib.py
skyfield/data/__init__.py
skyfield/data/constellations.gz
skyfield/data/constellations.npz
skyfield/data/delta_t.npz
skyfield/data/earth_orientation.py
skyfield/data/gravitational_parameters.py
skyfield/data/hipparcos.py
skyfield/data/historic_deltat.npy
skyfield/data/horizons.py
skyfield/data/iers.npz
skyfield/data/iers.py
skyfield/data/morrison_stephenson_deltat.npy
skyfield/data/mpc.py
skyfield/data/nutation.npz
skyfield/data/spice.py
skyfield/data/stellarium.py
skyfield/data/text_pck.py
skyfield/data/tycho2.py
skyfield/tests/__init__.py
skyfield/tests/conventions.py
skyfield/tests/fixes.py
skyfield/tests/test_against_horizons.py
skyfield/tests/test_against_novas.py
skyfield/tests/test_almanac.py
skyfield/tests/test_almanac_east_asia.py
skyfield/tests/test_almanac_searches.py
skyfield/tests/test_api.py
skyfield/tests/test_broadcastability.py
skyfield/tests/test_constellations.py
skyfield/tests/test_curves.py
skyfield/tests/test_data_iers.py
skyfield/tests/test_deflection.py
skyfield/tests/test_earth_satellites.py
skyfield/tests/test_earthlib.py
skyfield/tests/test_eclipselib.py
skyfield/tests/test_elementslib.py
skyfield-1.54.dist-info/LICENSE
skyfield-1.54.dist-info/METADATA
skyfield-1.54.dist-info/WHEEL
skyfield-1.54.dist-info/top_level.txt
skyfield-1.54.dist-info/RECORD
