Metadata-Version: 2.1
Name: skyfield
Version: 1.54
Summary: Elegant astronomy for Python
Home-page: http://github.com/brandon-rhodes/python-skyfield/
Author: Brandon Rhodes
Author-email: brandon@rhodesmill.org
License: MIT
Classifier: Development Status :: 5 - Production/Stable
Classifier: Intended Audience :: Developers
Classifier: Intended Audience :: Education
Classifier: Intended Audience :: Science/Research
Classifier: License :: OSI Approved :: MIT License
Classifier: Programming Language :: Python :: 2.7
Classifier: Programming Language :: Python :: 3.7
Classifier: Programming Language :: Python :: 3.8
Classifier: Programming Language :: Python :: 3.9
Classifier: Programming Language :: Python :: 3.10
Classifier: Programming Language :: Python :: 3.11
Classifier: Programming Language :: Python :: 3.12
Classifier: Programming Language :: Python :: 3.13
Classifier: Topic :: Scientific/Engineering :: Astronomy
License-File: LICENSE
Requires-Dist: certifi>=2017.4.17
Requires-Dist: jplephem>=2.13
Requires-Dist: numpy
Requires-Dist: sgp4>=2.13
